{
  "imagePath": "vibe-coder-final.png",
  "metadata": null,
  "name": "vibe-coder",
  "type": "PLANAR",
  "properties": {
    "left": 0,
    "top": 0,
    "width": 640,
    "height": 640,
    "isRotated": false,
    "originalWidth": 640,
    "originalHeight": 640
  },
  "resources": {
    "originalImage": "vibe-coder-final.png",
    "croppedImage": "vibe-coder-final.png",
    "thumbnailImage": "vibe-coder-final.png",
    "luminanceImage": "vibe-coder-final.png"
  },
  "created": 1773469372225,
  "updated": 1773469372225
}
